loki_logger_handler/__init__.py
loki_logger_handler/loki_logger_handler.py
loki_logger_handler/loki_request.py
loki_logger_handler/stream.py
loki_logger_handler/streams.py
loki_logger_handler/formatters/__init__.py
loki_logger_handler/formatters/logger_formatter.py
loki_logger_handler/formatters/loguru_formatter.py
loki_logger_handler-1.1.2.dist-info/licenses/LICENSE
loki_logger_handler-1.1.2.dist-info/METADATA
loki_logger_handler-1.1.2.dist-info/WHEEL
loki_logger_handler-1.1.2.dist-info/top_level.txt
loki_logger_handler-1.1.2.dist-info/RECORD
